Experiment_1/Experiment_1.v
`timescale 1ns/1ps

module sum_N(input clk, input[2:0] N, input N_valid_in, input sum_ack, input reset, output reg[4:0] sum_out, output reg sum_valid);
parameter IDLE = 2'b00;
parameter BUSY = 2'b01;
parameter DONE = 2'b11;

wire [2:0] i_mux_out;
wire [4:0] add_out;
wire [4:0] sum_mux_out;
wire i_eq_1, i_eq_1_state;

reg [2:0] i;
reg [1:0] state;
reg [1:0] next_state;

assign i_mux_out = N_valid ? N : i-1;
assign add_out = sum_out + i;
assign sum_mux_out = N_valid ? 0 : ((state == DONE) ? sum_mux_out : add_out);
assign i_eq_1 = (i==1);
assign i_eq_1_state = i_eq_1 && (state == BUSY);
assign N_valid = N_valid_in && (state == IDLE);

always @(posedge clk or posedge reset)
if(reset)
begin
    sum_out <= 0;
    i <= 0;
    sum_valid <= 0;
end
else
begin
    sum_out <= sum_mux_out;
    i <= i_mux_out;
    sum_valid <= i_eq_1_state;
end

always @(*)
begin
case(state)
    IDLE : if(N_valid) next_state = BUSY; else next_state = IDLE;
    BUSY : if(sum_valid) next_state = DONE; else next_state = BUSY;
    DONE : if(sum_ack) next_state = IDLE; else next_state = DONE;
endcase  
end

always @(posedge clk or posedge reset)
if(reset)
begin
    state <= IDLE;
end
else
begin
    state <= next_state;
end
endmodule

Expt_1_testbench.v
`timescale 1ns/1ps
`include "VLSI_Experiment_1.v"
module Expt_1_tb();
reg clk;
reg [2:0] N;
reg N_valid;
reg sum_ack;
reg reset;
wire [4:0] sum_out;
wire sum_valid;

initial begin
    clk <= 0;
    forever begin
        #10;
        clk <= ~clk;
    end
end

sum_N sum_N(.clk(clk), .N(N), .N_valid_in(N_valid), .sum_ack(sum_ack), .reset(reset), .sum_out(sum_out), .sum_valid(sum_valid));

initial begin
    $dumpfile("dump.vcd");
    $dumpvars(0, sum_N);
    reset <= 1'b1;
    sum_ack <=  0;
    #20;
    reset <= 1'b0;
    N_valid <= 1;
    N <= 3'b111;
    #10;
    N_valid <= 0;
    #300;
    sum_ack <= 1;
    #10;
    sum_ack <= 0;
    #400;
    $finish;
end

endmodule

Experiment_1/Expt_1.vcd
$date
	Wed Mar 17 23:35:41 2021
$end
$version
	Icarus Verilog
$end
$timescale
	1ps
$end
$scope module Expt_1_tb $end
$scope module sum_N $end
$var wire 3 ! N [2:0] $end
$var wire 1 " N_valid $end
$var wire 1 # N_valid_in $end
$var wire 1 $ clk $end
$var wire 1 % i_eq_1_state $end
$var wire 1 & reset $end
$var wire 1 ' sum_ack $end
$var wire 5 ( sum_mux_out [4:0] $end
$var wire 3 ) i_mux_out [2:0] $end
$var wire 1 * i_eq_1 $end
$var wire 5 + add_out [4:0] $end
$var reg 3 , i [2:0] $end
$var reg 2 - next_state [1:0] $end
$var reg 2 . state [1:0] $end
$var reg 5 / sum_out [4:0] $end
$var reg 1 0 sum_valid $end
$upscope $end
$upscope $end
$enddefinitions $end
#0
$dumpvars
00
b0 /
b0 .
b0 -
b0 ,
b0 +
0*
bx )
b0 (
0'
1&
0%
0$
x#
x"
bx !
$end
#10000
1$
#20000
b1 -
b111 )
1"
0$
b111 !
1#
0&
#30000
b111 (
b110 )
b111 +
b111 ,
b1 .
b1 -
0"
1$
0#
#40000
0$
#50000
b1101 (
b101 )
b110 ,
b1101 +
b111 /
1$
#60000
0$
#70000
b10010 (
b100 )
b101 ,
b10010 +
b1101 /
1$
#80000
0$
#90000
b10110 (
b11 )
b100 ,
b10110 +
b10010 /
1$
#100000
0$
#110000
b11001 (
b10 )
b11 ,
b11001 +
b10110 /
1$
#120000
0$
#130000
b11011 (
b1 )
b10 ,
b11011 +
b11001 /
1$
#140000
0$
#150000
b11100 (
b0 )
1%
1*
b1 ,
b11100 +
b11011 /
1$
#160000
0$
#170000
b11 -
b111 )
0%
10
0*
b0 ,
b11100 +
b11100 /
1$
#180000
0$
#190000
b110 )
00
b11 +
b111 ,
b11 .
1$
#200000
0$
#210000
b101 )
b10 +
b110 ,
1$
#220000
0$
#230000
b100 )
b1 +
b101 ,
1$
#240000
0$
#250000
b11 )
b0 +
b100 ,
1$
#260000
0$
#270000
b10 )
b11111 +
b11 ,
1$
#280000
0$
#290000
b1 )
b11110 +
b10 ,
1$
#300000
0$
#310000
b0 )
b11101 +
1*
b1 ,
1$
#320000
0$
#330000
b111 )
b0 .
b11100 +
0*
b0 ,
b0 -
1$
1'
#340000
0$
0'
#350000
b11 (
b110 )
b11 +
b111 ,
1$
#360000
0$
#370000
b1001 (
b101 )
b110 ,
b1001 +
b11 /
1$
#380000
0$
#390000
b1110 (
b100 )
b101 ,
b1110 +
b1001 /
1$
#400000
0$
#410000
b10010 (
b11 )
b100 ,
b10010 +
b1110 /
1$
#420000
0$
#430000
b10101 (
b10 )
b11 ,
b10101 +
b10010 /
1$
#440000
0$
#450000
b10111 (
b1 )
b10 ,
b10111 +
b10101 /
1$
#460000
0$
#470000
b11000 (
b0 )
1*
b1 ,
b11000 +
b10111 /
1$
#480000
0$
#490000
b111 )
0*
b0 ,
b11000 +
b11000 /
1$
#500000
0$
#510000
b11111 (
b110 )
b11111 +
b111 ,
1$
#520000
0$
#530000
b101 (
b101 )
b110 ,
b101 +
b11111 /
1$
#540000
0$
#550000
b1010 (
b100 )
b101 ,
b1010 +
b101 /
1$
#560000
0$
#570000
b1110 (
b11 )
b100 ,
b1110 +
b1010 /
1$
#580000
0$
#590000
b10001 (
b10 )
b11 ,
b10001 +
b1110 /
1$
#600000
0$
#610000
b10011 (
b1 )
b10 ,
b10011 +
b10001 /
1$
#620000
0$
#630000
b10100 (
b0 )
1*
b1 ,
b10100 +
b10011 /
1$
#640000
0$
#650000
b111 )
0*
b0 ,
b10100 +
b10100 /
1$
#660000
0$
#670000
b11011 (
b110 )
b11011 +
b111 ,
1$
#680000
0$
#690000
b1 (
b101 )
b110 ,
b1 +
b11011 /
1$
#700000
0$
#710000
b110 (
b100 )
b101 ,
b110 +
b1 /
1$
#720000
0$
#730000
b1010 (
b11 )
b100 ,
b1010 +
b110 /
1$
