Experiment_2/Experiment_2.v
`timescale 1ns/1ps

module GCD (
    input clk,
    input [7:0] A_in,
    input [7:0] B_in,
    input input_valid,
    input reset,
    input gcd_ack,
    output [7:0] G_out,
    output output_valid
);

parameter IDLE = 2'b00;
parameter BUSY = 2'b01;
parameter DONE = 2'b10;

reg [7:0] A;
reg [7:0] B;
reg [1:0] state;
reg [1:0] next_state;

wire [7:0] A_mux_out;
wire [7:0] B_mux_out;
wire [7:0] A_out;
wire [7:0] B_out;
wire [7:0] G_out;
wire [7:0] A_minus_B;
wire B_zero;

assign A_out = A;
assign B_out = B;
assign A_mux_out = input_valid ? A_in : ( (state==BUSY) ? ((A_out < B_out) ? B_out : A_minus_B) : A_out);
assign B_mux_out = input_valid ? B_in : ( (state==BUSY) ? ((A_out < B_out) ? A_out : B_out) : B_out);
assign A_minus_B = A_out - B_out;
assign B_zero = (B_out == 8'b00000000);

always @(posedge clk or posedge reset)
if(reset)
begin
    A <= 0;
    B <= 0;
end
else
begin
    A <= A_mux_out;
    B <= B_mux_out;
end

always @(posedge clk or posedge reset)
begin
if(reset)
    state <= IDLE;
else
    state <= next_state;
end

assign G_out = output_valid ? A_out : 0;
assign output_valid = (state == DONE);

always @(*)
begin
case (state)
    IDLE: if(input_valid) next_state = BUSY; else next_state = IDLE;
    BUSY: if(B_zero) next_state = DONE; else next_state = BUSY;
    DONE: if(gcd_ack) next_state = IDLE; else next_state = DONE;
endcase
end

endmodule

Experiment_2/Expt_2_tb.v
`timescale 1ns/1ps
`include "Experiment_2.v"
module Expt_2_tb ();

reg clk;
reg [7:0] A_in;
reg [7:0] B_in;
reg input_valid;
reg reset;
reg gcd_ack;
wire [7:0] G_out;
wire output_valid;

initial begin
    clk <= 0;
    forever begin
        #10;
        clk <= ~clk;
    end
end

GCD GCD(.clk(clk), .A_in(A_in), .B_in(B_in), .input_valid(input_valid), .reset(reset), .gcd_ack(gcd_ack), .G_out(G_out), .output_valid(output_valid));

initial begin
    $dumpfile("dump.vcd");
    $dumpvars(0, GCD);
    reset <= 1;
    #10;
    reset <= 0;
    #10;
    input_valid <= 0;
    A_in <= 21;
    B_in <= 18;
    #30;
    input_valid <= 1;
    #10;
    input_valid <= 0;
    #300;
    gcd_ack <= 1;
    #15;
    gcd_ack <= 0;
    #50;
    input_valid <= 1;
    #10;
    input_valid <= 0;
    #300;

    $finish;
end
    
endmodule

Experiment_2/dump.vcd
$date
	Fri Apr  2 17:07:47 2021
$end
$version
	Icarus Verilog
$end
$timescale
	1ps
$end
$scope module Expt_2_tb $end
$scope module GCD $end
$var wire 8 ! A_in [7:0] $end
$var wire 8 " A_out [7:0] $end
$var wire 8 # B_in [7:0] $end
$var wire 8 $ B_out [7:0] $end
$var wire 1 % clk $end
$var wire 1 & gcd_ack $end
$var wire 1 ' input_valid $end
$var wire 1 ( reset $end
$var wire 1 ) output_valid $end
$var wire 8 * G_out [7:0] $end
$var wire 1 + B_zero $end
$var wire 8 , B_mux_out [7:0] $end
$var wire 8 - A_mux_out [7:0] $end
$var wire 8 . A_minus_B [7:0] $end
$var reg 8 / A [7:0] $end
$var reg 8 0 B [7:0] $end
$var reg 2 1 next_state [1:0] $end
$var reg 2 2 state [1:0] $end
$upscope $end
$upscope $end
$enddefinitions $end
#0
$dumpvars
b0 2
b0 1
b0 0
b0 /
b0 .
bx -
bx ,
1+
b0 *
0)
1(
x'
x&
0%
b0 $
bx #
b0 "
bx !
$end
#10000
x+
bx $
bx 0
bx .
bx "
bx /
0(
1%
#20000
b10010 #
b10101 !
0'
0%
#30000
1%
#40000
0%
#50000
b1 2
b11 .
0+
b10010 $
b10010 0
b10101 "
b10101 /
b1 1
b10101 -
b10010 ,
1%
1'
#60000
b11 -
0%
0'
#70000
b11 ,
b10010 -
b11110001 .
b11 "
b11 /
1%
#80000
0%
#90000
b1111 -
b11 $
b11 0
b1111 .
b10010 "
b10010 /
1%
#100000
0%
#110000
b1100 -
b1100 .
b1111 "
b1111 /
1%
#120000
0%
#130000
b1001 -
b1001 .
b1100 "
b1100 /
1%
#140000
0%
#150000
b110 -
b110 .
b1001 "
b1001 /
1%
#160000
0%
#170000
b11 -
b11 .
b110 "
b110 /
1%
#180000
0%
#190000
b0 -
b0 .
b11 "
b11 /
1%
#200000
0%
#210000
b0 ,
b11 -
b11111101 .
b0 "
b0 /
1%
#220000
0%
#230000
b10 1
1+
b0 $
b0 0
b11 .
b11 "
b11 /
1%
#240000
0%
#250000
b11 *
1)
b10 2
1%
#260000
0%
#270000
1%
#280000
0%
#290000
1%
#300000
0%
#310000
1%
#320000
0%
#330000
1%
#340000
0%
#350000
1%
#360000
b0 1
0%
1&
#370000
b0 *
0)
b0 2
1%
#375000
0&
#380000
0%
#390000
1%
#400000
0%
#410000
1%
#420000
0%
#425000
b1 1
b10101 -
b10010 ,
1'
#430000
0+
b10010 $
b10010 0
b11 .
b10101 "
b10101 /
b1 2
1%
#435000
b11 -
0'
#440000
0%
#450000
b11 ,
b10010 -
b11110001 .
b11 "
b11 /
1%
#460000
0%
#470000
b1111 -
b11 $
b11 0
b1111 .
b10010 "
b10010 /
1%
#480000
0%
#490000
b1100 -
b1100 .
b1111 "
b1111 /
1%
#500000
0%
#510000
b1001 -
b1001 .
b1100 "
b1100 /
1%
#520000
0%
#530000
b110 -
b110 .
b1001 "
b1001 /
1%
#540000
0%
#550000
b11 -
b11 .
b110 "
b110 /
1%
#560000
0%
#570000
b0 -
b0 .
b11 "
b11 /
1%
#580000
0%
#590000
b0 ,
b11 -
b11111101 .
b0 "
b0 /
1%
#600000
0%
#610000
b10 1
1+
b0 $
b0 0
b11 .
b11 "
b11 /
1%
#620000
0%
#630000
b11 *
1)
b10 2
1%
